xgoedu/__init__.py
xgolib/__init__.py
xgoscreen/LCD_2inch.py
xgoscreen/__init__.py
xgoscreen/lcdconfig.py
xgo_pythonlib-0.3.0.dist-info/METADATA
xgo_pythonlib-0.3.0.dist-info/WHEEL
xgo_pythonlib-0.3.0.dist-info/top_level.txt
xgo_pythonlib-0.3.0.dist-info/RECORD
