Metadata-Version: 2.1
Name: xgo-pythonlib
Version: 0.3.0
Summary: PythonLib for XGO2-DOG
Home-page: https://github.com/Xgorobot/XGO-PythonLib
Author: luwudynamics
Author-email: hello@xgorobot.com
License: MIT
Classifier: License :: OSI Approved :: MIT License
Classifier: Programming Language :: Python
Classifier: Programming Language :: Python :: 3
Classifier: Programming Language :: Python :: 3.6
Classifier: Programming Language :: Python :: Implementation :: CPython
Classifier: Programming Language :: Python :: Implementation :: PyPy
Requires-Python: >=3.6.0
